{"url":"https://s100.lv/lv/rss","lang":"fr","_id":"0iTPXziLkQOHwhf0"}
{"url":"https://s100.lv/ru/rss","lang":"en","_id":"2dExEXc3i2lnGHSo"}
{"url":"https://s100.lv/ru/rss","lang":"en","_id":"3HVsDa8FeyiAfGSN"}
{"url":"https://s100.lv/ru/rss","lang":"en","_id":"3Hwos5octShITtGZ"}
{"url":"https://s100.lv/ru/rss","lang":"en","_id":"5mPqu2zUY3NdfVXN"}
{"url":"https://s100.lv/lv/rss","lang":"fr","_id":"INjHFuNR4d6LvMbO"}
{"url":"https://s100.lv/ru/rss","lang":"en","_id":"IuJLPnjYcchQacJc"}
{"url":"https://s100.lv/lv/rss","lang":"fr","_id":"NtvE1LaE4O5Tc0Zw"}
{"url":"https://s100.lv/lv/rss","lang":"fr","_id":"tPZ8nq5cuQmZcWfq"}
{"url":"https://s100.lv/lv/rss","lang":"fr","_id":"vhYMz5eIijgvNmop"}
{"url":"https://s100.lv/ru/rss","lang":"en","_id":"uJabOrZEN4DakjXJ"}
{"url":"https://s100.lv/lv/rss","lang":"fr","_id":"bUeUyoNxvV8oYsDp"}
